panoramabridge.py
panoramabridge-0.1.9rc4.dist-info/licenses/LICENSE
panoramabridge-0.1.9rc4.dist-info/METADATA
panoramabridge-0.1.9rc4.dist-info/WHEEL
panoramabridge-0.1.9rc4.dist-info/entry_points.txt
panoramabridge-0.1.9rc4.dist-info/top_level.txt
panoramabridge-0.1.9rc4.dist-info/RECORD
