Metadata-Version: 2.4
Name: panoramabridge
Version: 0.1.9rc4
Summary: A Python Qt6 application for monitoring local directories and automatically transferring files to Panorama WebDAV servers
Author-email: Michael MacCoss <maccoss@uw.edu>
Maintainer-email: MacCoss Lab <maccoss@uw.edu>
License-Expression: Apache-2.0
Project-URL: Homepage, https://github.com/maccoss/PanoramaBridge
Project-URL: Repository, https://github.com/maccoss/PanoramaBridge
Project-URL: Documentation, https://github.com/maccoss/PanoramaBridge#readme
Project-URL: Issues, https://github.com/maccoss/PanoramaBridge/issues
Keywords: panorama,webdav,mass-spectrometry,file-transfer,proteomics,laboratory,automation,file-monitoring
Classifier: Development Status :: 4 - Beta
Classifier: Environment :: X11 Applications :: Qt
Classifier: Environment :: Win32 (MS Windows)
Classifier: Intended Audience :: Science/Research
Classifier: Operating System :: Microsoft :: Windows
Classifier: Operating System :: POSIX :: Linux
Classifier: Operating System :: MacOS
Classifier: Programming Language :: Python :: 3
Classifier: Programming Language :: Python :: 3.9
Classifier: Programming Language :: Python :: 3.10
Classifier: Programming Language :: Python :: 3.11
Classifier: Programming Language :: Python :: 3.12
Classifier: Topic :: Scientific/Engineering :: Bio-Informatics
Classifier: Topic :: System :: Filesystems
Classifier: Topic :: Internet :: File Transfer Protocol (FTP)
Requires-Python: >=3.9
License-File: LICENSE
Requires-Dist: PyQt6>=6.4.0
Requires-Dist: watchdog>=3.0.0
Requires-Dist: requests>=2.31.0
Requires-Dist: keyring>=24.0.0
Requires-Dist: keyrings.alt>=5.0.0
Provides-Extra: dev
Requires-Dist: pytest>=8.0.0; extra == "dev"
Requires-Dist: pytest-qt>=4.5.0; extra == "dev"
Requires-Dist: pytest-cov>=4.0.0; extra == "dev"
Requires-Dist: ruff>=0.1.0; extra == "dev"
Requires-Dist: mypy>=1.0.0; extra == "dev"
Requires-Dist: pre-commit>=3.0.0; extra == "dev"
Provides-Extra: test
Requires-Dist: pytest>=8.0.0; extra == "test"
Requires-Dist: pytest-qt>=4.5.0; extra == "test"
Requires-Dist: pytest-cov>=4.0.0; extra == "test"
Provides-Extra: build
Requires-Dist: pyinstaller>=6.0.0; extra == "build"
Dynamic: license-file
